setup.cfg
setup.py
pip_services3_facade/__init__.py
pip_services3_facade.egg-info/PKG-INFO
pip_services3_facade.egg-info/SOURCES.txt
pip_services3_facade.egg-info/dependency_links.txt
pip_services3_facade.egg-info/requires.txt
pip_services3_facade.egg-info/top_level.txt
pip_services3_facade.egg-info/zip-safe
pip_services3_facade/auth/BasicAuthManager.py
pip_services3_facade/auth/OwnerAuthManager.py
pip_services3_facade/auth/RoleAuthorizer.py
pip_services3_facade/auth/__init__.py
pip_services3_facade/build/FacadeFactory.py
pip_services3_facade/build/__init__.py
pip_services3_facade/container/FacadeProcess.py
pip_services3_facade/container/__init__.py
pip_services3_facade/operations/AboutOperations.py
pip_services3_facade/operations/FacadeOperations.py
pip_services3_facade/operations/__init__.py
pip_services3_facade/routes/FacadeRoutes.py
pip_services3_facade/routes/__init__.py
pip_services3_facade/services/FacadeService.py
pip_services3_facade/services/IFacadeService.py
pip_services3_facade/services/MainFacadeService.py
pip_services3_facade/services/PartitionFacadeService.py
pip_services3_facade/services/__init__.py